libertai_utils/__init__.py
libertai_utils/aleph/__init__.py
libertai_utils/aleph/program.py
libertai_utils/chains/__init__.py
libertai_utils/chains/ethereum.py
libertai_utils/chains/index.py
libertai_utils/chains/solana.py
libertai_utils/interfaces/__init__.py
libertai_utils/interfaces/blockchain.py
libertai_utils/utils/__init__.py
libertai_utils/utils/crypto.py
libertai_utils-0.0.16.dist-info/METADATA
libertai_utils-0.0.16.dist-info/WHEEL
libertai_utils-0.0.16.dist-info/RECORD
