Metadata-Version: 2.3
Name: libertai-utils
Version: 0.0.16
Summary: LibertAI internal types and functions
Author: LibertAI.io team
Author-email: hello@libertai.io
Requires-Python: >=3.11,<4.0
Classifier: Programming Language :: Python :: 3
Classifier: Programming Language :: Python :: 3.11
Classifier: Programming Language :: Python :: 3.12
Classifier: Programming Language :: Python :: 3.13
Classifier: Topic :: Scientific/Engineering :: Artificial Intelligence
Requires-Dist: eciespy (>=0.4.2,<0.5.0)
Requires-Dist: pydantic (>=2.10.6,<3.0.0)
Requires-Dist: pynacl (>=1.5.0,<2.0.0)
Requires-Dist: solders (>=0.22.0,<1.0.0)
Requires-Dist: web3 (>=7.10.0,<8.0.0)
Project-URL: Documentation, https://docs.libertai.io
Project-URL: Homepage, https://libertai.io
Project-URL: Repository, https://github.com/LibertAI/libertai-utils
